[
		{
			"provider": "aws",
			"node_types": [
				{
					"type": "t3.nano",
					"vCPU": 2,
					"cpu_credits": 6,
					"memory": {
						"value": 512,
						"unit": "MB"
					},
					"disk": {
						"value": 1,
						"unit": "TB"
					},
					"network_bandwidth": {
						"value": 625,
						"unit": "Mb"
					},
					"price": 0.0052,
					"latency_ms": 20,
					"requests_acceleration_factor": 1.0
				},
				{
					"type": "t3.micro",
					"vCPU": 2,
					"cpu_credits": 12,
					"memory": {
						"value": 1,
						"unit": "GB"
					},
					"disk": {
						"value": 1,
						"unit": "TB"
					},
					"network_bandwidth": {
						"value": 625,
						"unit": "Mb"
					},
					"price": 0.0104,
					"latency_ms": 20,
					"requests_acceleration_factor": 1.1
				},
				{
					"type": "t3.small",
					"vCPU": 2,
					"cpu_credits": 24,
					"memory": {
						"value": 2,
						"unit": "GB"
					},
					"disk": {
						"value": 1,
						"unit": "TB"
					},
					"network_bandwidth": {
						"value": 625,
						"unit": "Mb"
					},
					"price": 0.0209,
					"latency_ms": 20,
					"requests_acceleration_factor": 1.1
				},
				{
					"type": "t3.medium",
					"vCPU": 2,
					"cpu_credits": 24,
					"memory": {
						"value": 4,
						"unit": "GB"
					},
					"disk": {
						"value": 1,
						"unit": "TB"
					},
					"network_bandwidth": {
						"value": 625,
						"unit": "Mb"
					},
					"price": 0.0418,
					"latency_ms": 20,
					"requests_acceleration_factor": 1.1
				},
				{
					"type": "t3.large",
					"vCPU": 2,
					"cpu_credits": 36,
					"memory": {
						"value": 8,
						"unit": "GB"
					},
					"disk": {
						"value": 1,
						"unit": "TB"
					},
					"network_bandwidth": {
						"value": 625,
						"unit": "Mb"
					},
					"price": 0.0835,
					"latency_ms": 20,
					"requests_acceleration_factor": 1.1
				},
				{
					"type": "t3.xlarge",
					"vCPU": 4,
					"cpu_credits": 96,
					"memory": {
						"value": 16,
						"unit": "GB"
					},
					"disk": {
						"value": 1,
						"unit": "TB"
					},
					"network_bandwidth": {
						"value": 625,
						"unit": "Mb"
					},
					"price": 0.1670,
					"latency_ms": 20,
					"requests_acceleration_factor": 1.5
				},
				{
					"type": "t3.2xlarge",
					"vCPU": 8,
					"cpu_credits": 192,
					"memory": {
						"value": 32,
						"unit": "GB"
					},
					"disk": {
						"value": 1,
						"unit": "TB"
					},
					"network_bandwidth": {
						"value": 625,
						"unit": "Mb"
					},
					"price": 0.3341,
					"latency_ms": 20,
					"requests_acceleration_factor": 1.7
				}
			]
		}
]
